cryo_mcp/__init__.py
cryo_mcp/server.py
cryo_mcp/sql.py
cryo_mcp-0.1.5.dist-info/METADATA
cryo_mcp-0.1.5.dist-info/WHEEL
cryo_mcp-0.1.5.dist-info/entry_points.txt
cryo_mcp-0.1.5.dist-info/licenses/LICENSE
cryo_mcp-0.1.5.dist-info/RECORD
