Metadata-Version: 2.4
Name: cryo-mcp
Version: 0.1.5
Summary: MCP server for querying Ethereum blockchain data using cryo
Project-URL: Homepage, https://github.com/z80dev/cryo-mcp
Project-URL: Bug Tracker, https://github.com/z80dev/cryo-mcp/issues
Author-email: z80 <z80@ophy.xyz>
License: MIT License
License-File: LICENSE
Keywords: api,blockchain,cryo,ethereum,mcp,server
Classifier: Development Status :: 4 - Beta
Classifier: Intended Audience :: Developers
Classifier: License :: OSI Approved :: MIT License
Classifier: Programming Language :: Python :: 3
Classifier: Programming Language :: Python :: 3.8
Classifier: Programming Language :: Python :: 3.9
Classifier: Programming Language :: Python :: 3.10
Classifier: Programming Language :: Python :: 3.11
Classifier: Programming Language :: Python :: 3.12
Classifier: Topic :: Software Development :: Libraries :: Python Modules
Requires-Python: >=3.10
Requires-Dist: duckdb>=1.2.1
Requires-Dist: mcp>=1.3.0
Requires-Dist: numpy>=2.2.3
Requires-Dist: pandas>=2.2.3
Requires-Dist: pyarrow>=19.0.1
Requires-Dist: requests>=2.28.0
Provides-Extra: dev
Requires-Dist: black>=23.0.0; extra == 'dev'
Requires-Dist: isort>=5.10.0; extra == 'dev'
Requires-Dist: mypy>=1.0.0; extra == 'dev'
Requires-Dist: pytest>=7.0.0; extra == 'dev'
